{
  "deviceName": "linux_ubuntu_64_desktop_16.04_chrome_64",
  "displayName": "Chrome",
  "comparisonType": "Browser",
  "scoreTotal": 3.4,
  "testDate": "10\/2018",
  "totalScoreRanges": [
    {
      "range": "0-20",
      "binaries": [],
      "percentage": "0.0%"
    },
    {
      "range": "21-40",
      "binaries": [],
      "percentage": "0.0%"
    },
    {
      "range": "41-60",
      "binaries": [
        {
          "binary": "nacl_helper_bootstrap",
          "ASLR": 0.0,
          "fortification": "UNKNOWN_FORT",
          "stackGuards": false,
          "filePath": "\/opt\/google\/chrome\/nacl_helper_bootstrap",
          "_64bit": true,
          "CFI": null,
          "codeSize": 5355.0,
          "RELRO": 0.0,
          "DEP": true,
          "SafeSEH": null,
          "good": 0,
          "HEAP": null,
          "veryRisky": 0,
          "totalScore": 53.13,
          "extremelyRisky": 0,
          "type": "Executable",
          "risky": 0
        }
      ],
      "percentage": "12.5%"
    },
    {
      "range": "61-80",
      "binaries": [
        {
          "binary": "libwidevinecdmadapter.so",
          "ASLR": null,
          "fortification": "NOT_FORT",
          "stackGuards": true,
          "filePath": "\/opt\/google\/chrome\/libwidevinecdmadapter.so",
          "_64bit": true,
          "CFI": null,
          "codeSize": 384363.0,
          "RELRO": 0.0,
          "DEP": true,
          "SafeSEH": null,
          "good": 0,
          "HEAP": null,
          "veryRisky": 2,
          "totalScore": 65.63,
          "extremelyRisky": 0,
          "type": "Library",
          "risky": 409
        },
        {
          "binary": "libwidevinecdm.so",
          "ASLR": null,
          "fortification": "UNKNOWN_FORT",
          "stackGuards": false,
          "filePath": "\/opt\/google\/chrome\/libwidevinecdm.so",
          "_64bit": true,
          "CFI": null,
          "codeSize": 1638160.0,
          "RELRO": 1.0,
          "DEP": true,
          "SafeSEH": null,
          "good": 0,
          "HEAP": null,
          "veryRisky": 0,
          "totalScore": 68.75,
          "extremelyRisky": 0,
          "type": "Library",
          "risky": 2
        },
        {
          "binary": "libGLESv2.so",
          "ASLR": null,
          "fortification": "NOT_FORT",
          "stackGuards": true,
          "filePath": "\/opt\/google\/chrome\/swiftshader\/libGLESv2.so",
          "_64bit": true,
          "CFI": null,
          "codeSize": 2034424.0,
          "RELRO": 1.0,
          "DEP": true,
          "SafeSEH": null,
          "good": 0,
          "HEAP": null,
          "veryRisky": 27,
          "totalScore": 71.88,
          "extremelyRisky": 0,
          "type": "Library",
          "risky": 752
        },
        {
          "binary": "libEGL.so",
          "ASLR": null,
          "fortification": "NOT_FORT",
          "stackGuards": true,
          "filePath": "\/opt\/google\/chrome\/swiftshader\/libEGL.so",
          "_64bit": true,
          "CFI": null,
          "codeSize": 343912.0,
          "RELRO": 1.0,
          "DEP": true,
          "SafeSEH": null,
          "good": 0,
          "HEAP": null,
          "veryRisky": 2,
          "totalScore": 71.88,
          "extremelyRisky": 0,
          "type": "Library",
          "risky": 392
        },
        {
          "binary": "chrome-sandbox",
          "ASLR": 0.0,
          "fortification": "MIXED_FORT",
          "stackGuards": true,
          "filePath": "\/opt\/google\/chrome\/chrome-sandbox",
          "_64bit": true,
          "CFI": null,
          "codeSize": 3821.0,
          "RELRO": 1.0,
          "DEP": true,
          "SafeSEH": null,
          "good": 1,
          "HEAP": null,
          "veryRisky": 0,
          "totalScore": 75.0,
          "extremelyRisky": 0,
          "type": "Executable",
          "risky": 7
        },
        {
          "binary": "nacl_helper",
          "ASLR": 1.0,
          "fortification": "MIXED_FORT",
          "stackGuards": true,
          "filePath": "\/opt\/google\/chrome\/nacl_helper",
          "_64bit": true,
          "CFI": null,
          "codeSize": 2086882.0,
          "RELRO": 1.0,
          "DEP": true,
          "SafeSEH": null,
          "good": 0,
          "HEAP": null,
          "veryRisky": 15,
          "totalScore": 78.13,
          "extremelyRisky": 0,
          "type": "Executable",
          "risky": 745
        },
        {
          "binary": "chrome",
          "ASLR": 1.0,
          "fortification": "MIXED_FORT",
          "stackGuards": true,
          "filePath": "\/opt\/google\/chrome\/chrome",
          "_64bit": true,
          "CFI": null,
          "codeSize": 91324488.0,
          "RELRO": 1.0,
          "DEP": true,
          "SafeSEH": null,
          "good": 0,
          "HEAP": null,
          "veryRisky": 266,
          "totalScore": 78.13,
          "extremelyRisky": 0,
          "type": "Executable",
          "risky": 32117
        }
      ],
      "percentage": "87.5%"
    },
    {
      "range": "81-100",
      "binaries": [],
      "percentage": "0.0%"
    }
  ],
  "operatingSystemVersion": "Ubuntu Desktop 16.04",
  "operatingSystem": "Linux",
  "deviceVersion": "63.0.3239.132"
}